Workbook

Sheet Inicio
B2: PRESUPUESTO FAMILIAR · INICIO
B3: Una base clara para organizar el dinero del hogar
B4: Libro nativo construido desde 29 fuentes de templates/sources · las celdas amarillas son editables.
B6: CÓMO USARLO | G6: PARÁMETROS RÁPIDOS
B7: 01 | C7: Configura el hogar | E7: Cambia mes, ingresos, ahorro y miembros en Listas. | G7: Mes seleccionado | H7: =Listas!$C$8 -> Enero
B8: 02 | C8: Planifica los meses | E8: Completa la matriz Presupuesto con tus importes. | G8: Ingresos netos | H8: =Listas!$C$9 -> 3200
B9: 03 | C9: Registra cada movimiento | E9: Movimientos alimenta Gastos reales y Flujo de caja. | G9: Ahorro objetivo | H9: =Listas!$C$10 -> 300
B10: 04 | C10: Revisa y decide | E10: Resumen, Metas y Deudas convierten los datos en acciones. | G10: Miembro A | H10: =Listas!$C$11 -> Ana
G11: Miembro B | H11: =Listas!$C$12 -> Carlos
B14: MAPA DEL LIBRO
B15: Resumen | C15: Panel mensual con indicadores, desviación por categoría y gráfico.
B16: Presupuesto | C16: Matriz anual planificada, inspirada en los libros mensuales y anuales.
B17: Gastos reales | C17: Matriz calculada a partir del registro de movimientos.
B18: Movimientos | C18: Diario de ingresos, gastos y ahorros con listas desplegables.
B19: Flujo de caja | C19: Lectura mensual de ingresos, gastos, ahorro y disponible.
B20: Metas y fondo | C20: Fondo de emergencia y objetivos con progreso y fecha.
B21: Deudas | C21: Pagos comprometidos, interés estimado y meses restantes.
B22: Listas | C22: Parámetros editables y catálogos que alimentan las validaciones.
B25: Consejo: duplica el archivo antes de iniciar un nuevo año. El encuadre y las fórmulas quedan protegidos por una estructura simple, visible y fácil de adaptar.

Sheet Resumen
B2: PRESUPUESTO FAMILIAR · RESUMEN
B3: El mes, en una sola pantalla
B4: Panel de decisión inspirado en los balances, reportes mensuales y comparaciones presupuesto/real de las fuentes.
B5: Mes seleccionado | C5: =Listas!$C$8 -> Enero
B6: INGRESOS REALES | E6: GASTOS REALES | H6: AHORRO REAL | K6: DISPONIBLE
B7: =INDEX('Flujo de caja'!$D$8:$D$19,MATCH($C$5,'Flujo de caja'!$B$8:$B$19,0)) -> 3200 | E7: =INDEX('Flujo de caja'!$F$8:$F$19,MATCH($C$5,'Flujo de caja'!$B$8:$B$19,0)) -> 225 | H7: =INDEX('Flujo de caja'!$H$8:$H$19,MATCH($C$5,'Flujo de caja'!$B$8:$B$19,0)) -> 250 | K7: =INDEX('Flujo de caja'!$I$8:$I$19,MATCH($C$5,'Flujo de caja'!$B$8:$B$19,0)) -> 2725
B10: GASTO POR CATEGORÍA
B11: Categoría | C11: Plan | D11: Real | E11: Diferencia | F11: % gastado
B12: =Presupuesto!B8 -> Vivienda | C12: =INDEX(Presupuesto!$C$8:$N$14,MATCH($B12,Presupuesto!$B$8:$B$14,0),MATCH($C$5,Presupuesto!$C$7:$N$7,0)) -> 1100 | D12: =INDEX('Gastos reales'!$C$8:$N$14,MATCH($B12,'Gastos reales'!$B$8:$B$14,0),MATCH($C$5,'Gastos reales'!$C$7:$N$7,0)) -> 62 | E12: =C12-D12 -> 1038 | F12: =IFERROR(D12/C12,0) -> 0.056363636
B13: =Presupuesto!B9 -> Alimentación | C13: =INDEX(Presupuesto!$C$8:$N$14,MATCH($B13,Presupuesto!$B$8:$B$14,0),MATCH($C$5,Presupuesto!$C$7:$N$7,0)) -> 420 | D13: =INDEX('Gastos reales'!$C$8:$N$14,MATCH($B13,'Gastos reales'!$B$8:$B$14,0),MATCH($C$5,'Gastos reales'!$C$7:$N$7,0)) -> 86 | E13: =C13-D13 -> 334 | F13: =IFERROR(D13/C13,0) -> 0.2047619
B14: =Presupuesto!B10 -> Transporte | C14: =INDEX(Presupuesto!$C$8:$N$14,MATCH($B14,Presupuesto!$B$8:$B$14,0),MATCH($C$5,Presupuesto!$C$7:$N$7,0)) -> 250 | D14: =INDEX('Gastos reales'!$C$8:$N$14,MATCH($B14,'Gastos reales'!$B$8:$B$14,0),MATCH($C$5,'Gastos reales'!$C$7:$N$7,0)) -> 48 | E14: =C14-D14 -> 202 | F14: =IFERROR(D14/C14,0) -> 0.192
B15: =Presupuesto!B11 -> Salud | C15: =INDEX(Presupuesto!$C$8:$N$14,MATCH($B15,Presupuesto!$B$8:$B$14,0),MATCH($C$5,Presupuesto!$C$7:$N$7,0)) -> 350 | D15: =INDEX('Gastos reales'!$C$8:$N$14,MATCH($B15,'Gastos reales'!$B$8:$B$14,0),MATCH($C$5,'Gastos reales'!$C$7:$N$7,0)) -> 29 | E15: =C15-D15 -> 321 | F15: =IFERROR(D15/C15,0) -> 0.082857143
B16: =Presupuesto!B12 -> Educación | C16: =INDEX(Presupuesto!$C$8:$N$14,MATCH($B16,Presupuesto!$B$8:$B$14,0),MATCH($C$5,Presupuesto!$C$7:$N$7,0)) -> 140 | D16: =INDEX('Gastos reales'!$C$8:$N$14,MATCH($B16,'Gastos reales'!$B$8:$B$14,0),MATCH($C$5,'Gastos reales'!$C$7:$N$7,0)) -> 0 | E16: =C16-D16 -> 140 | F16: =IFERROR(D16/C16,0) -> 0
B17: =Presupuesto!B13 -> Ocio | C17: =INDEX(Presupuesto!$C$8:$N$14,MATCH($B17,Presupuesto!$B$8:$B$14,0),MATCH($C$5,Presupuesto!$C$7:$N$7,0)) -> 280 | D17: =INDEX('Gastos reales'!$C$8:$N$14,MATCH($B17,'Gastos reales'!$B$8:$B$14,0),MATCH($C$5,'Gastos reales'!$C$7:$N$7,0)) -> 0 | E17: =C17-D17 -> 280 | F17: =IFERROR(D17/C17,0) -> 0
B18: =Presupuesto!B14 -> Otros | C18: =INDEX(Presupuesto!$C$8:$N$14,MATCH($B18,Presupuesto!$B$8:$B$14,0),MATCH($C$5,Presupuesto!$C$7:$N$7,0)) -> 160 | D18: =INDEX('Gastos reales'!$C$8:$N$14,MATCH($B18,'Gastos reales'!$B$8:$B$14,0),MATCH($C$5,'Gastos reales'!$C$7:$N$7,0)) -> 0 | E18: =C18-D18 -> 160 | F18: =IFERROR(D18/C18,0) -> 0
B19: TOTAL | C19: =SUM(C12:C18) -> 2700 | D19: =SUM(D12:D18) -> 225 | E19: =SUM(E12:E18) -> 2475 | F19: =IFERROR(D19/C19,0) -> 0.083333333
B22: La diferencia es Plan - Real: positiva = queda margen; negativa = la categoría ha superado lo previsto.

Sheet Presupuesto
B2: PRESUPUESTO FAMILIAR · PRESUPUESTO
B3: Presupuesto planificado por mes
B4: Matriz anual con la distribución temporal que se repite en los ejemplos de presupuesto personal, ventas y empresas.
B6: PLAN ANUAL · CELDAS AMARILLAS = ENTRADA
B7: Categoría | C7: Enero | D7: Febrero | E7: Marzo | F7: Abril | G7: Mayo | H7: Junio | I7: Julio | J7: Agosto | K7: Septiembre | L7: Octubre | M7: Noviembre | N7: Diciembre | O7: Total anual
B8: Vivienda | C8: 1100 | D8: 1100 | E8: 1100 | F8: 1100 | G8: 1100 | H8: 1100 | I8: 1100 | J8: 1100 | K8: 1100 | L8: 1100 | M8: 1100 | N8: 1100 | O8: =SUM(C8:N8) -> 13200
B9: Alimentación | C9: 420 | D9: 420 | E9: 430 | F9: 430 | G9: 440 | H9: 440 | I9: 460 | J9: 460 | K9: 440 | L9: 440 | M9: 460 | N9: 500 | O9: =SUM(C9:N9) -> 5340
B10: Transporte | C10: 250 | D10: 250 | E10: 250 | F10: 250 | G10: 250 | H10: 250 | I10: 250 | J10: 250 | K10: 250 | L10: 250 | M10: 250 | N10: 250 | O10: =SUM(C10:N10) -> 3000
B11: Salud | C11: 350 | D11: 350 | E11: 350 | F11: 350 | G11: 350 | H11: 350 | I11: 350 | J11: 350 | K11: 350 | L11: 350 | M11: 350 | N11: 500 | O11: =SUM(C11:N11) -> 4350
B12: Educación | C12: 140 | D12: 140 | E12: 140 | F12: 140 | G12: 140 | H12: 140 | I12: 180 | J12: 180 | K12: 180 | L12: 180 | M12: 180 | N12: 180 | O12: =SUM(C12:N12) -> 1920
B13: Ocio | C13: 280 | D13: 280 | E13: 300 | F13: 300 | G13: 320 | H13: 320 | I13: 420 | J13: 420 | K13: 300 | L13: 300 | M13: 340 | N13: 450 | O13: =SUM(C13:N13) -> 4030
B14: Otros | C14: 160 | D14: 160 | E14: 170 | F14: 170 | G14: 180 | H14: 180 | I14: 190 | J14: 190 | K14: 180 | L14: 180 | M14: 200 | N14: 220 | O14: =SUM(C14:N14) -> 2180
B15: TOTAL DEL HOGAR | C15: =SUM(C8:C14) -> 2700 | D15: =SUM(D8:D14) -> 2700 | E15: =SUM(E8:E14) -> 2740 | F15: =SUM(F8:F14) -> 2740 | G15: =SUM(G8:G14) -> 2780 | H15: =SUM(H8:H14) -> 2780 | I15: =SUM(I8:I14) -> 2950 | J15: =SUM(J8:J14) -> 2950 | ... O15: =SUM(O8:O14) -> 34020
B18: La matriz conserva el patrón de los presupuestos mensual/anual: categorías en filas, meses en columnas y total anual calculado a la derecha.

Sheet Gastos reales
B2: PRESUPUESTO FAMILIAR · GASTOS REALES
B3: Gasto real calculado desde los movimientos
B4: Cada importe se obtiene del diario de movimientos; no hace falta duplicar la entrada en dos hojas.
B6: REAL ACUMULADO · FÓRMULAS AZULES
B7: Categoría | C7: Enero | D7: Febrero | E7: Marzo | F7: Abril | G7: Mayo | H7: Junio | I7: Julio | J7: Agosto | K7: Septiembre | L7: Octubre | M7: Noviembre | N7: Diciembre | O7: Total anual
B8: =Presupuesto!B8 -> Vivienda | C8: =SUMIFS(Movimientos!$G$8:$G$200,Movimientos!$D$8:$D$200,"Gasto",Movimientos!$E$8:$E$200,$B8,Movimientos!$C$8:$C$200,C$7) -> 62 | D8: =SUMIFS(Movimientos!$G$8:$G$200,Movimientos!$D$8:$D$200,"Gasto",Movimientos!$E$8:$E$200,$B8,Movimientos!$C$8:$C$200,D$7) -> 0 | E8: =SUMIFS(Movimientos!$G$8:$G$200,Movimientos!$D$8:$D$200,"Gasto",Movimientos!$E$8:$E$200,$B8,Movimientos!$C$8:$C$200,E$7) -> 0 | F8: =SUMIFS(Movimientos!$G$8:$G$200,Movimientos!$D$8:$D$200,"Gasto",Movimientos!$E$8:$E$200,$B8,Movimientos!$C$8:$C$200,F$7) -> 0 | G8: =SUMIFS(Movimientos!$G$8:$G$200,Movimientos!$D$8:$D$200,"Gasto",Movimientos!$E$8:$E$200,$B8,Movimientos!$C$8:$C$200,G$7) -> 0 | H8: =SUMIFS(Movimientos!$G$8:$G$200,Movimientos!$D$8:$D$200,"Gasto",Movimientos!$E$8:$E$200,$B8,Movimientos!$C$8:$C$200,H$7) -> 0 | I8: =SUMIFS(Movimientos!$G$8:$G$200,Movimientos!$D$8:$D$200,"Gasto",Movimientos!$E$8:$E$200,$B8,Movimientos!$C$8:$C$200,I$7) -> 0 | J8: =SUMIFS(Movimientos!$G$8:$G$200,Movimientos!$D$8:$D$200,"Gasto",Movimientos!$E$8:$E$200,$B8,Movimientos!$C$8:$C$200,J$7) -> 0 | ... N8: =SUMIFS(Movimientos!$G$8:$G$200,Movimientos!$D$8:$D$200,"Gasto",Movimientos!$E$8:$E$200,$B8,Movimientos!$C$8:$C$200,N$7) -> 0 | O8: =SUM(C8:N8) -> 62
B9: =Presupuesto!B9 -> Alimentación | C9: =SUMIFS(Movimientos!$G$8:$G$200,Movimientos!$D$8:$D$200,"Gasto",Movimientos!$E$8:$E$200,$B9,Movimientos!$C$8:$C$200,C$7) -> 86 | D9: =SUMIFS(Movimientos!$G$8:$G$200,Movimientos!$D$8:$D$200,"Gasto",Movimientos!$E$8:$E$200,$B9,Movimientos!$C$8:$C$200,D$7) -> 0 | E9: =SUMIFS(Movimientos!$G$8:$G$200,Movimientos!$D$8:$D$200,"Gasto",Movimientos!$E$8:$E$200,$B9,Movimientos!$C$8:$C$200,E$7) -> 0 | F9: =SUMIFS(Movimientos!$G$8:$G$200,Movimientos!$D$8:$D$200,"Gasto",Movimientos!$E$8:$E$200,$B9,Movimientos!$C$8:$C$200,F$7) -> 0 | G9: =SUMIFS(Movimientos!$G$8:$G$200,Movimientos!$D$8:$D$200,"Gasto",Movimientos!$E$8:$E$200,$B9,Movimientos!$C$8:$C$200,G$7) -> 0 | H9: =SUMIFS(Movimientos!$G$8:$G$200,Movimientos!$D$8:$D$200,"Gasto",Movimientos!$E$8:$E$200,$B9,Movimientos!$C$8:$C$200,H$7) -> 0 | I9: =SUMIFS(Movimientos!$G$8:$G$200,Movimientos!$D$8:$D$200,"Gasto",Movimientos!$E$8:$E$200,$B9,Movimientos!$C$8:$C$200,I$7) -> 0 | J9: =SUMIFS(Movimientos!$G$8:$G$200,Movimientos!$D$8:$D$200,"Gasto",Movimientos!$E$8:$E$200,$B9,Movimientos!$C$8:$C$200,J$7) -> 0 | ... N9: =SUMIFS(Movimientos!$G$8:$G$200,Movimientos!$D$8:$D$200,"Gasto",Movimientos!$E$8:$E$200,$B9,Movimientos!$C$8:$C$200,N$7) -> 0 | O9: =SUM(C9:N9) -> 86
B10: =Presupuesto!B10 -> Transporte | C10: =SUMIFS(Movimientos!$G$8:$G$200,Movimientos!$D$8:$D$200,"Gasto",Movimientos!$E$8:$E$200,$B10,Movimientos!$C$8:$C$200,C$7) -> 48 | D10: =SUMIFS(Movimientos!$G$8:$G$200,Movimientos!$D$8:$D$200,"Gasto",Movimientos!$E$8:$E$200,$B10,Movimientos!$C$8:$C$200,D$7) -> 0 | E10: =SUMIFS(Movimientos!$G$8:$G$200,Movimientos!$D$8:$D$200,"Gasto",Movimientos!$E$8:$E$200,$B10,Movimientos!$C$8:$C$200,E$7) -> 0 | F10: =SUMIFS(Movimientos!$G$8:$G$200,Movimientos!$D$8:$D$200,"Gasto",Movimientos!$E$8:$E$200,$B10,Movimientos!$C$8:$C$200,F$7) -> 0 | G10: =SUMIFS(Movimientos!$G$8:$G$200,Movimientos!$D$8:$D$200,"Gasto",Movimientos!$E$8:$E$200,$B10,Movimientos!$C$8:$C$200,G$7) -> 0 | H10: =SUMIFS(Movimientos!$G$8:$G$200,Movimientos!$D$8:$D$200,"Gasto",Movimientos!$E$8:$E$200,$B10,Movimientos!$C$8:$C$200,H$7) -> 0 | I10: =SUMIFS(Movimientos!$G$8:$G$200,Movimientos!$D$8:$D$200,"Gasto",Movimientos!$E$8:$E$200,$B10,Movimientos!$C$8:$C$200,I$7) -> 0 | J10: =SUMIFS(Movimientos!$G$8:$G$200,Movimientos!$D$8:$D$200,"Gasto",Movimientos!$E$8:$E$200,$B10,Movimientos!$C$8:$C$200,J$7) -> 0 | ... N10: =SUMIFS(Movimientos!$G$8:$G$200,Movimientos!$D$8:$D$200,"Gasto",Movimientos!$E$8:$E$200,$B10,Movimientos!$C$8:$C$200,N$7) -> 0 | O10: =SUM(C10:N10) -> 48
B11: =Presupuesto!B11 -> Salud | C11: =SUMIFS(Movimientos!$G$8:$G$200,Movimientos!$D$8:$D$200,"Gasto",Movimientos!$E$8:$E$200,$B11,Movimientos!$C$8:$C$200,C$7) -> 29 | D11: =SUMIFS(Movimientos!$G$8:$G$200,Movimientos!$D$8:$D$200,"Gasto",Movimientos!$E$8:$E$200,$B11,Movimientos!$C$8:$C$200,D$7) -> 0 | E11: =SUMIFS(Movimientos!$G$8:$G$200,Movimientos!$D$8:$D$200,"Gasto",Movimientos!$E$8:$E$200,$B11,Movimientos!$C$8:$C$200,E$7) -> 0 | F11: =SUMIFS(Movimientos!$G$8:$G$200,Movimientos!$D$8:$D$200,"Gasto",Movimientos!$E$8:$E$200,$B11,Movimientos!$C$8:$C$200,F$7) -> 0 | G11: =SUMIFS(Movimientos!$G$8:$G$200,Movimientos!$D$8:$D$200,"Gasto",Movimientos!$E$8:$E$200,$B11,Movimientos!$C$8:$C$200,G$7) -> 0 | H11: =SUMIFS(Movimientos!$G$8:$G$200,Movimientos!$D$8:$D$200,"Gasto",Movimientos!$E$8:$E$200,$B11,Movimientos!$C$8:$C$200,H$7) -> 0 | I11: =SUMIFS(Movimientos!$G$8:$G$200,Movimientos!$D$8:$D$200,"Gasto",Movimientos!$E$8:$E$200,$B11,Movimientos!$C$8:$C$200,I$7) -> 0 | J11: =SUMIFS(Movimientos!$G$8:$G$200,Movimientos!$D$8:$D$200,"Gasto",Movimientos!$E$8:$E$200,$B11,Movimientos!$C$8:$C$200,J$7) -> 0 | ... N11: =SUMIFS(Movimientos!$G$8:$G$200,Movimientos!$D$8:$D$200,"Gasto",Movimientos!$E$8:$E$200,$B11,Movimientos!$C$8:$C$200,N$7) -> 0 | O11: =SUM(C11:N11) -> 29
B12: =Presupuesto!B12 -> Educación | C12: =SUMIFS(Movimientos!$G$8:$G$200,Movimientos!$D$8:$D$200,"Gasto",Movimientos!$E$8:$E$200,$B12,Movimientos!$C$8:$C$200,C$7) -> 0 | D12: =SUMIFS(Movimientos!$G$8:$G$200,Movimientos!$D$8:$D$200,"Gasto",Movimientos!$E$8:$E$200,$B12,Movimientos!$C$8:$C$200,D$7) -> 0 | E12: =SUMIFS(Movimientos!$G$8:$G$200,Movimientos!$D$8:$D$200,"Gasto",Movimientos!$E$8:$E$200,$B12,Movimientos!$C$8:$C$200,E$7) -> 0 | F12: =SUMIFS(Movimientos!$G$8:$G$200,Movimientos!$D$8:$D$200,"Gasto",Movimientos!$E$8:$E$200,$B12,Movimientos!$C$8:$C$200,F$7) -> 0 | G12: =SUMIFS(Movimientos!$G$8:$G$200,Movimientos!$D$8:$D$200,"Gasto",Movimientos!$E$8:$E$200,$B12,Movimientos!$C$8:$C$200,G$7) -> 0 | H12: =SUMIFS(Movimientos!$G$8:$G$200,Movimientos!$D$8:$D$200,"Gasto",Movimientos!$E$8:$E$200,$B12,Movimientos!$C$8:$C$200,H$7) -> 0 | I12: =SUMIFS(Movimientos!$G$8:$G$200,Movimientos!$D$8:$D$200,"Gasto",Movimientos!$E$8:$E$200,$B12,Movimientos!$C$8:$C$200,I$7) -> 0 | J12: =SUMIFS(Movimientos!$G$8:$G$200,Movimientos!$D$8:$D$200,"Gasto",Movimientos!$E$8:$E$200,$B12,Movimientos!$C$8:$C$200,J$7) -> 0 | ... N12: =SUMIFS(Movimientos!$G$8:$G$200,Movimientos!$D$8:$D$200,"Gasto",Movimientos!$E$8:$E$200,$B12,Movimientos!$C$8:$C$200,N$7) -> 0 | O12: =SUM(C12:N12) -> 0
B13: =Presupuesto!B13 -> Ocio | C13: =SUMIFS(Movimientos!$G$8:$G$200,Movimientos!$D$8:$D$200,"Gasto",Movimientos!$E$8:$E$200,$B13,Movimientos!$C$8:$C$200,C$7) -> 0 | D13: =SUMIFS(Movimientos!$G$8:$G$200,Movimientos!$D$8:$D$200,"Gasto",Movimientos!$E$8:$E$200,$B13,Movimientos!$C$8:$C$200,D$7) -> 0 | E13: =SUMIFS(Movimientos!$G$8:$G$200,Movimientos!$D$8:$D$200,"Gasto",Movimientos!$E$8:$E$200,$B13,Movimientos!$C$8:$C$200,E$7) -> 0 | F13: =SUMIFS(Movimientos!$G$8:$G$200,Movimientos!$D$8:$D$200,"Gasto",Movimientos!$E$8:$E$200,$B13,Movimientos!$C$8:$C$200,F$7) -> 0 | G13: =SUMIFS(Movimientos!$G$8:$G$200,Movimientos!$D$8:$D$200,"Gasto",Movimientos!$E$8:$E$200,$B13,Movimientos!$C$8:$C$200,G$7) -> 0 | H13: =SUMIFS(Movimientos!$G$8:$G$200,Movimientos!$D$8:$D$200,"Gasto",Movimientos!$E$8:$E$200,$B13,Movimientos!$C$8:$C$200,H$7) -> 0 | I13: =SUMIFS(Movimientos!$G$8:$G$200,Movimientos!$D$8:$D$200,"Gasto",Movimientos!$E$8:$E$200,$B13,Movimientos!$C$8:$C$200,I$7) -> 0 | J13: =SUMIFS(Movimientos!$G$8:$G$200,Movimientos!$D$8:$D$200,"Gasto",Movimientos!$E$8:$E$200,$B13,Movimientos!$C$8:$C$200,J$7) -> 0 | ... N13: =SUMIFS(Movimientos!$G$8:$G$200,Movimientos!$D$8:$D$200,"Gasto",Movimientos!$E$8:$E$200,$B13,Movimientos!$C$8:$C$200,N$7) -> 0 | O13: =SUM(C13:N13) -> 0
B14: =Presupuesto!B14 -> Otros | C14: =SUMIFS(Movimientos!$G$8:$G$200,Movimientos!$D$8:$D$200,"Gasto",Movimientos!$E$8:$E$200,$B14,Movimientos!$C$8:$C$200,C$7) -> 0 | D14: =SUMIFS(Movimientos!$G$8:$G$200,Movimientos!$D$8:$D$200,"Gasto",Movimientos!$E$8:$E$200,$B14,Movimientos!$C$8:$C$200,D$7) -> 0 | E14: =SUMIFS(Movimientos!$G$8:$G$200,Movimientos!$D$8:$D$200,"Gasto",Movimientos!$E$8:$E$200,$B14,Movimientos!$C$8:$C$200,E$7) -> 0 | F14: =SUMIFS(Movimientos!$G$8:$G$200,Movimientos!$D$8:$D$200,"Gasto",Movimientos!$E$8:$E$200,$B14,Movimientos!$C$8:$C$200,F$7) -> 0 | G14: =SUMIFS(Movimientos!$G$8:$G$200,Movimientos!$D$8:$D$200,"Gasto",Movimientos!$E$8:$E$200,$B14,Movimientos!$C$8:$C$200,G$7) -> 0 | H14: =SUMIFS(Movimientos!$G$8:$G$200,Movimientos!$D$8:$D$200,"Gasto",Movimientos!$E$8:$E$200,$B14,Movimientos!$C$8:$C$200,H$7) -> 0 | I14: =SUMIFS(Movimientos!$G$8:$G$200,Movimientos!$D$8:$D$200,"Gasto",Movimientos!$E$8:$E$200,$B14,Movimientos!$C$8:$C$200,I$7) -> 0 | J14: =SUMIFS(Movimientos!$G$8:$G$200,Movimientos!$D$8:$D$200,"Gasto",Movimientos!$E$8:$E$200,$B14,Movimientos!$C$8:$C$200,J$7) -> 0 | ... N14: =SUMIFS(Movimientos!$G$8:$G$200,Movimientos!$D$8:$D$200,"Gasto",Movimientos!$E$8:$E$200,$B14,Movimientos!$C$8:$C$200,N$7) -> 0 | O14: =SUM(C14:N14) -> 0
B15: TOTAL DEL HOGAR | C15: =SUM(C8:C14) -> 225 | D15: =SUM(D8:D14) -> 0 | E15: =SUM(E8:E14) -> 0 | F15: =SUM(F8:F14) -> 0 | G15: =SUM(G8:G14) -> 0 | H15: =SUM(H8:H14) -> 0 | I15: =SUM(I8:I14) -> 0 | J15: =SUM(J8:J14) -> 0 | ... O15: =SUM(O8:O14) -> 225
B18: La hoja sigue el patrón de los ejemplos de presupuesto versus gastado, pero centraliza el dato real en Movimientos para evitar descuadres.

Sheet Movimientos
B2: PRESUPUESTO FAMILIAR · MOVIMIENTOS
B3: Diario de ingresos, gastos y ahorros
B4: Registra cada operación una sola vez; las hojas de análisis la agrupan por mes y categoría.
B6: REGISTRO OPERATIVO · ENTRADA MANUAL | K6: REGLAS DEL DIARIO
B7: Fecha | C7: Mes | D7: Tipo | E7: Categoría | F7: Concepto | G7: Importe | H7: Pagado por | I7: Estado | K7: Una fila = una operación. Usa Tipo para separar ingresos, gastos y ahorros; no introduzcas un gasto manual también en Gastos reales.
B8: 46392 | C8: Enero | D8: Gasto | E8: Alimentación | F8: Compra semanal | G8: 86 | H8: Familia | I8: Conciliado
B9: 46395 | C9: Enero | D9: Gasto | E9: Vivienda | F9: Electricidad | G9: 62 | H9: Familia | I9: Conciliado
B10: 46399 | C10: Enero | D10: Gasto | E10: Transporte | F10: Abono mensual | G10: 48 | H10: Ana | I10: Pendiente
B11: 46406 | C11: Enero | D11: Gasto | E11: Salud | F11: Farmacia | G11: 29 | H11: Carlos | I11: Conciliado
B12: 46412 | C12: Enero | D12: Ingreso | E12: Otros | F12: Nómina | G12: 3200 | H12: Familia | I12: Conciliado | K12: Las listas desplegables mantienen consistentes los nombres que usan los resúmenes y gráficos.
B13: 46415 | C13: Enero | D13: Ahorro | E13: Otros | F13: Fondo de emergencia | G13: 250 | H13: Familia | I13: Pendiente

Sheet Flujo de caja
B2: PRESUPUESTO FAMILIAR · FLUJO DE CAJA
B3: Flujo de caja mensual
B4: La lectura anual combina ingresos, gastos planificados, movimientos reales, ahorro y saldo disponible.
B6: LECTURA MENSUAL
B7: Mes | C7: Ingresos plan | D7: Ingresos real | E7: Gastos plan | F7: Gastos real | G7: Ahorro plan | H7: Ahorro real | I7: Disponible | J7: Comentarios
B8: Enero | C8: =Listas!$C$9 -> 3200 | D8: =SUMIFS(Movimientos!$G$8:$G$200,Movimientos!$D$8:$D$200,"Ingreso",Movimientos!$C$8:$C$200,$B8) -> 3200 | E8: =SUM(INDEX(Presupuesto!$C$8:$N$14,0,ROW()-7)) -> 2700 | F8: =SUM(INDEX('Gastos reales'!$C$8:$N$14,0,ROW()-7)) -> 225 | G8: =Listas!$C$10 -> 300 | H8: =SUMIFS(Movimientos!$G$8:$G$200,Movimientos!$D$8:$D$200,"Ahorro",Movimientos!$C$8:$C$200,$B8) -> 250 | I8: =D8-F8-H8 -> 2725
B9: Febrero | C9: =Listas!$C$9 -> 3200 | D9: =SUMIFS(Movimientos!$G$8:$G$200,Movimientos!$D$8:$D$200,"Ingreso",Movimientos!$C$8:$C$200,$B9) -> 0 | E9: =SUM(INDEX(Presupuesto!$C$8:$N$14,0,ROW()-7)) -> 2700 | F9: =SUM(INDEX('Gastos reales'!$C$8:$N$14,0,ROW()-7)) -> 0 | G9: =Listas!$C$10 -> 300 | H9: =SUMIFS(Movimientos!$G$8:$G$200,Movimientos!$D$8:$D$200,"Ahorro",Movimientos!$C$8:$C$200,$B9) -> 0 | I9: =D9-F9-H9 -> 0
B10: Marzo | C10: =Listas!$C$9 -> 3200 | D10: =SUMIFS(Movimientos!$G$8:$G$200,Movimientos!$D$8:$D$200,"Ingreso",Movimientos!$C$8:$C$200,$B10) -> 0 | E10: =SUM(INDEX(Presupuesto!$C$8:$N$14,0,ROW()-7)) -> 2740 | F10: =SUM(INDEX('Gastos reales'!$C$8:$N$14,0,ROW()-7)) -> 0 | G10: =Listas!$C$10 -> 300 | H10: =SUMIFS(Movimientos!$G$8:$G$200,Movimientos!$D$8:$D$200,"Ahorro",Movimientos!$C$8:$C$200,$B10) -> 0 | I10: =D10-F10-H10 -> 0
B11: Abril | C11: =Listas!$C$9 -> 3200 | D11: =SUMIFS(Movimientos!$G$8:$G$200,Movimientos!$D$8:$D$200,"Ingreso",Movimientos!$C$8:$C$200,$B11) -> 0 | E11: =SUM(INDEX(Presupuesto!$C$8:$N$14,0,ROW()-7)) -> 2740 | F11: =SUM(INDEX('Gastos reales'!$C$8:$N$14,0,ROW()-7)) -> 0 | G11: =Listas!$C$10 -> 300 | H11: =SUMIFS(Movimientos!$G$8:$G$200,Movimientos!$D$8:$D$200,"Ahorro",Movimientos!$C$8:$C$200,$B11) -> 0 | I11: =D11-F11-H11 -> 0
B12: Mayo | C12: =Listas!$C$9 -> 3200 | D12: =SUMIFS(Movimientos!$G$8:$G$200,Movimientos!$D$8:$D$200,"Ingreso",Movimientos!$C$8:$C$200,$B12) -> 0 | E12: =SUM(INDEX(Presupuesto!$C$8:$N$14,0,ROW()-7)) -> 2780 | F12: =SUM(INDEX('Gastos reales'!$C$8:$N$14,0,ROW()-7)) -> 0 | G12: =Listas!$C$10 -> 300 | H12: =SUMIFS(Movimientos!$G$8:$G$200,Movimientos!$D$8:$D$200,"Ahorro",Movimientos!$C$8:$C$200,$B12) -> 0 | I12: =D12-F12-H12 -> 0
B13: Junio | C13: =Listas!$C$9 -> 3200 | D13: =SUMIFS(Movimientos!$G$8:$G$200,Movimientos!$D$8:$D$200,"Ingreso",Movimientos!$C$8:$C$200,$B13) -> 0 | E13: =SUM(INDEX(Presupuesto!$C$8:$N$14,0,ROW()-7)) -> 2780 | F13: =SUM(INDEX('Gastos reales'!$C$8:$N$14,0,ROW()-7)) -> 0 | G13: =Listas!$C$10 -> 300 | H13: =SUMIFS(Movimientos!$G$8:$G$200,Movimientos!$D$8:$D$200,"Ahorro",Movimientos!$C$8:$C$200,$B13) -> 0 | I13: =D13-F13-H13 -> 0
B14: Julio | C14: =Listas!$C$9 -> 3200 | D14: =SUMIFS(Movimientos!$G$8:$G$200,Movimientos!$D$8:$D$200,"Ingreso",Movimientos!$C$8:$C$200,$B14) -> 0 | E14: =SUM(INDEX(Presupuesto!$C$8:$N$14,0,ROW()-7)) -> 2950 | F14: =SUM(INDEX('Gastos reales'!$C$8:$N$14,0,ROW()-7)) -> 0 | G14: =Listas!$C$10 -> 300 | H14: =SUMIFS(Movimientos!$G$8:$G$200,Movimientos!$D$8:$D$200,"Ahorro",Movimientos!$C$8:$C$200,$B14) -> 0 | I14: =D14-F14-H14 -> 0
B15: Agosto | C15: =Listas!$C$9 -> 3200 | D15: =SUMIFS(Movimientos!$G$8:$G$200,Movimientos!$D$8:$D$200,"Ingreso",Movimientos!$C$8:$C$200,$B15) -> 0 | E15: =SUM(INDEX(Presupuesto!$C$8:$N$14,0,ROW()-7)) -> 2950 | F15: =SUM(INDEX('Gastos reales'!$C$8:$N$14,0,ROW()-7)) -> 0 | G15: =Listas!$C$10 -> 300 | H15: =SUMIFS(Movimientos!$G$8:$G$200,Movimientos!$D$8:$D$200,"Ahorro",Movimientos!$C$8:$C$200,$B15) -> 0 | I15: =D15-F15-H15 -> 0
B16: Septiembre | C16: =Listas!$C$9 -> 3200 | D16: =SUMIFS(Movimientos!$G$8:$G$200,Movimientos!$D$8:$D$200,"Ingreso",Movimientos!$C$8:$C$200,$B16) -> 0 | E16: =SUM(INDEX(Presupuesto!$C$8:$N$14,0,ROW()-7)) -> 2800 | F16: =SUM(INDEX('Gastos reales'!$C$8:$N$14,0,ROW()-7)) -> 0 | G16: =Listas!$C$10 -> 300 | H16: =SUMIFS(Movimientos!$G$8:$G$200,Movimientos!$D$8:$D$200,"Ahorro",Movimientos!$C$8:$C$200,$B16) -> 0 | I16: =D16-F16-H16 -> 0
B17: Octubre | C17: =Listas!$C$9 -> 3200 | D17: =SUMIFS(Movimientos!$G$8:$G$200,Movimientos!$D$8:$D$200,"Ingreso",Movimientos!$C$8:$C$200,$B17) -> 0 | E17: =SUM(INDEX(Presupuesto!$C$8:$N$14,0,ROW()-7)) -> 2800 | F17: =SUM(INDEX('Gastos reales'!$C$8:$N$14,0,ROW()-7)) -> 0 | G17: =Listas!$C$10 -> 300 | H17: =SUMIFS(Movimientos!$G$8:$G$200,Movimientos!$D$8:$D$200,"Ahorro",Movimientos!$C$8:$C$200,$B17) -> 0 | I17: =D17-F17-H17 -> 0
B18: Noviembre | C18: =Listas!$C$9 -> 3200 | D18: =SUMIFS(Movimientos!$G$8:$G$200,Movimientos!$D$8:$D$200,"Ingreso",Movimientos!$C$8:$C$200,$B18) -> 0 | E18: =SUM(INDEX(Presupuesto!$C$8:$N$14,0,ROW()-7)) -> 2880 | F18: =SUM(INDEX('Gastos reales'!$C$8:$N$14,0,ROW()-7)) -> 0 | G18: =Listas!$C$10 -> 300 | H18: =SUMIFS(Movimientos!$G$8:$G$200,Movimientos!$D$8:$D$200,"Ahorro",Movimientos!$C$8:$C$200,$B18) -> 0 | I18: =D18-F18-H18 -> 0
B19: Diciembre | C19: =Listas!$C$9 -> 3200 | D19: =SUMIFS(Movimientos!$G$8:$G$200,Movimientos!$D$8:$D$200,"Ingreso",Movimientos!$C$8:$C$200,$B19) -> 0 | E19: =SUM(INDEX(Presupuesto!$C$8:$N$14,0,ROW()-7)) -> 3200 | F19: =SUM(INDEX('Gastos reales'!$C$8:$N$14,0,ROW()-7)) -> 0 | G19: =Listas!$C$10 -> 300 | H19: =SUMIFS(Movimientos!$G$8:$G$200,Movimientos!$D$8:$D$200,"Ahorro",Movimientos!$C$8:$C$200,$B19) -> 0 | I19: =D19-F19-H19 -> 0
B20: TOTAL ANUAL | C20: =SUM(C8:C19) -> 38400 | D20: =SUM(D8:D19) -> 3200 | E20: =SUM(E8:E19) -> 34020 | F20: =SUM(F8:F19) -> 225 | G20: =SUM(G8:G19) -> 3600 | H20: =SUM(H8:H19) -> 250 | I20: =SUM(I8:I19) -> 2725
B23: El saldo disponible se calcula como ingreso real menos gasto real y ahorro real; sirve como señal de revisión, no como asesoramiento financiero.

Sheet Metas y fondo
B2: PRESUPUESTO FAMILIAR · METAS Y FONDO
B3: Metas de ahorro y fondo de emergencia
B4: El bloque de metas recoge el patrón de fondo necesario, ahorro acumulado, pendiente y fecha de logro.
B6: PARÁMETROS DE LA META
B7: Mes actual | C7: =Listas!$C$8 -> Enero | E7: Inflación mensual | F7: 0.02 | H7: Ahorro mensual | I7: =Listas!$C$10 -> 300
B9: Meta | C9: Gasto mensual | D9: Meses | E9: Meta necesaria | F9: Ahorrado | G9: Pendiente | H9: Progreso | I9: Fecha objetivo | J9: Estado
B10: Fondo de emergencia | C10: 2400 | D10: 6 | E10: =C10*D10 -> 14400 | F10: 2500 | G10: =MAX(E10-F10,0) -> 11900 | H10: =IFERROR(F10/E10,0) -> 0.17361111 | I10: 46752 | J10: =IF(H10>=1,"Completa","En curso") -> En curso
B11: Vacaciones | C11: 450 | D11: 4 | E11: =C11*D11 -> 1800 | F11: 650 | G11: =MAX(E11-F11,0) -> 1150 | H11: =IFERROR(F11/E11,0) -> 0.36111111 | I11: 46568 | J11: =IF(H11>=1,"Completa","En curso") -> En curso
B12: Reparaciones del hogar | C12: 300 | D12: 4 | E12: =C12*D12 -> 1200 | F12: 300 | G12: =MAX(E12-F12,0) -> 900 | H12: =IFERROR(F12/E12,0) -> 0.25 | I12: 46691 | J12: =IF(H12>=1,"Completa","En curso") -> En curso
B13: TOTAL | E13: =SUM(E10:E12) -> 17400 | F13: =SUM(F10:F12) -> 3450 | G13: =SUM(G10:G12) -> 13950 | H13: =IFERROR(F13/E13,0) -> 0.19827586
B16: El fondo de emergencia se expresa como meses de gasto, igual que en las fuentes de fondo de emergencia; las demás metas pueden usar un objetivo directo cambiando Meses a 1.

Sheet Deudas
B2: PRESUPUESTO FAMILIAR · DEUDAS
B3: Deudas y pagos comprometidos
B4: Bloque compacto inspirado en las hojas de comparación de hipotecas y amortización del préstamo.
B6: OBLIGACIONES ABIERTAS
B7: Deuda | C7: Saldo actual | D7: Interés anual | E7: Pago mensual | F7: Meses restantes | G7: Interés estimado | H7: Estado
B8: Hipoteca | C8: 180000 | D8: 0.035 | E8: 850 | F8: 240 | G8: =C8*D8*E8/12 -> 446250 | H8: =IF(E8>0,"Activa","Pagada") -> Activa
B9: Préstamo coche | C9: 9200 | D9: 0.07 | E9: 280 | F9: 36 | G9: =C9*D9*E9/12 -> 15026.667 | H9: =IF(E9>0,"Activa","Pagada") -> Activa
B10: Tarjeta | C10: 2400 | D10: 0.19 | E10: 150 | F10: 18 | G10: =C10*D10*E10/12 -> 5700 | H10: =IF(E10>0,"Activa","Pagada") -> Activa
B11: TOTAL | C11: =SUM(C8:C10) -> 191600 | E11: =SUM(E8:E10) -> 1280 | G11: =SUM(G8:G10) -> 466976.67
B14: El interés estimado es una señal orientativa basada en saldo × tasa × meses / 12; para una amortización contractual completa, sustituye este bloque por un calendario específico.

Sheet Listas
B2: PRESUPUESTO FAMILIAR · LISTAS
B3: Parámetros y catálogos editables
B4: Cambia aquí los valores amarillos; las listas alimentan las validaciones del resto del libro.
B6: PARÁMETROS DEL HOGAR | E6: MESES | G6: TIPOS | I6: CATEGORÍAS | K6: MIEMBROS | M6: ESTADOS
B7: Parámetro | C7: Valor | E7: Enero | G7: Ingreso | I7: Vivienda | K7: Ana | M7: Conciliado
B8: Mes seleccionado | C8: Enero | E8: Febrero | G8: Gasto | I8: Alimentación | K8: Carlos | M8: Pendiente
B9: Ingresos netos mensuales | C9: 3200 | E9: Marzo | G9: Ahorro | I9: Transporte | K9: Familia
B10: Ahorro mensual objetivo | C10: 300 | E10: Abril | I10: Salud
B11: Miembro A | C11: Ana | E11: Mayo | I11: Educación
B12: Miembro B | C12: Carlos | E12: Junio | I12: Ocio
B13: Moneda | C13: EUR | E13: Julio | I13: Otros
E14: Agosto
E15: Septiembre
E16: Octubre
E17: Noviembre
E18: Diciembre
E21: Las listas son visibles para que las futuras plantillas puedan sustituir categorías sin esconder la lógica del libro.
