Workbook

Sheet Inicio
B2: PLANIFICADOR DE BODA · INICIO
B3: Organiza tu boda con una visión clara
B4: Presupuesto, proveedores, pagos, invitados y tareas en un solo libro.
B6: CÓMO USARLO | G6: PARÁMETROS RÁPIDOS
C7: Define la celebración | E7: Fecha, presupuesto e invitados en Listas. | G7: Fecha de boda | H7: =Listas!$C$8 -> 46557
C8: Planifica el presupuesto | E8: Distribuye los importes por categoría y momento. | G8: Presupuesto objetivo | H8: =Listas!$C$9 -> 18000
C9: Registra proveedores | E9: Anota contratos, pagos pendientes y responsables. | G9: Invitados previstos | H9: =Listas!$C$10 -> 120
C10: Cierra cada decisión | E10: Usa Checklist, Invitados y Resumen para avanzar. | G10: Pareja A | H10: =Listas!$C$11 -> Laura
G11: Pareja B | H11: =Listas!$C$12 -> Álvaro
B14: MAPA DEL LIBRO
B15: Resumen | C15: Visión general del presupuesto, pagos, pendientes e invitados confirmados.
B16: Presupuesto | C16: Plan anual por categorías y calendario de desembolsos.
B17: Pagos reales | C17: Importes pagados y comparativa frente al plan.
B18: Proveedores | C18: Registro de contratos, pagos, responsables y estados.
B19: Flujo de pagos | C19: Lectura mensual de presupuesto, pagos y saldo previsto.
B20: Checklist | C20: Tareas clave con responsables, fechas y progreso.
B21: Invitados | C21: Conteo por grupo, confirmación, menú y mesa.
B22: Listas | C22: Parámetros y catálogos editables del libro.
B25: Consejo: duplica el archivo para cada boda y cambia primero las celdas de Listas. La estructura, la navegación y las fórmulas ya están preparadas para crecer sin perder el encuadre.

Sheet Resumen
B2: PLANIFICADOR DE BODA · RESUMEN
B3: El estado de la boda en una sola pantalla
B4: Panel de decisión para presupuesto, pagos, pendientes e invitados confirmados.
B5: Fecha de boda | C5: =Listas!$C$8 -> 46557
B6: PRESUPUESTO PLANIFICADO | E6: PAGOS REALES | H6: PENDIENTE | K6: INVITADOS CONFIRMADOS
B7: =SUM(Presupuesto!C8:N14) -> 17200 | E7: =SUMIFS(Proveedores!$G$8:$G$200,Proveedores!$D$8:$D$200,"Pago") -> 3750 | H7: =B7-E7 -> 13450 | K7: =Invitados!D11 -> 98
B10: PRESUPUESTO Y PAGOS POR CATEGORÍA
B11: Categoría | C11: Plan | D11: Pagado | E11: Pendiente | F11: % pagado
B12: =Presupuesto!B8 -> Lugar y ceremonia | C12: =SUM(Presupuesto!C8:N8) -> 3500 | D12: =SUMIFS(Proveedores!$G$8:$G$200,Proveedores!$D$8:$D$200,"Pago",Proveedores!$E$8:$E$200,$B12) -> 2000 | E12: =C12-D12 -> 1500 | F12: =IFERROR(D12/C12,0) -> 0.57142857
B13: =Presupuesto!B9 -> Banquete | C13: =SUM(Presupuesto!C9:N9) -> 5000 | D13: =SUMIFS(Proveedores!$G$8:$G$200,Proveedores!$D$8:$D$200,"Pago",Proveedores!$E$8:$E$200,$B13) -> 0 | E13: =C13-D13 -> 5000 | F13: =IFERROR(D13/C13,0) -> 0
B14: =Presupuesto!B10 -> Fotografía y vídeo | C14: =SUM(Presupuesto!C10:N10) -> 1800 | D14: =SUMIFS(Proveedores!$G$8:$G$200,Proveedores!$D$8:$D$200,"Pago",Proveedores!$E$8:$E$200,$B14) -> 600 | E14: =C14-D14 -> 1200 | F14: =IFERROR(D14/C14,0) -> 0.33333333
B15: =Presupuesto!B11 -> Música | C15: =SUM(Presupuesto!C11:N11) -> 1200 | D15: =SUMIFS(Proveedores!$G$8:$G$200,Proveedores!$D$8:$D$200,"Pago",Proveedores!$E$8:$E$200,$B15) -> 0 | E15: =C15-D15 -> 1200 | F15: =IFERROR(D15/C15,0) -> 0
B16: =Presupuesto!B12 -> Decoración y flores | C16: =SUM(Presupuesto!C12:N12) -> 1600 | D16: =SUMIFS(Proveedores!$G$8:$G$200,Proveedores!$D$8:$D$200,"Pago",Proveedores!$E$8:$E$200,$B16) -> 0 | E16: =C16-D16 -> 1600 | F16: =IFERROR(D16/C16,0) -> 0
B17: =Presupuesto!B13 -> Vestuario y belleza | C17: =SUM(Presupuesto!C13:N13) -> 2000 | D17: =SUMIFS(Proveedores!$G$8:$G$200,Proveedores!$D$8:$D$200,"Pago",Proveedores!$E$8:$E$200,$B17) -> 800 | E17: =C17-D17 -> 1200 | F17: =IFERROR(D17/C17,0) -> 0.4
B18: =Presupuesto!B14 -> Papelería y detalles | C18: =SUM(Presupuesto!C14:N14) -> 2100 | D18: =SUMIFS(Proveedores!$G$8:$G$200,Proveedores!$D$8:$D$200,"Pago",Proveedores!$E$8:$E$200,$B18) -> 350 | E18: =C18-D18 -> 1750 | F18: =IFERROR(D18/C18,0) -> 0.16666667
B19: TOTAL | C19: =SUM(C12:C18) -> 17200 | D19: =SUM(D12:D18) -> 3750 | E19: =SUM(E12:E18) -> 13450 | F19: =IFERROR(D19/C19,0) -> 0.21802326
B22: La diferencia es Plan - Pagado: positiva = aún queda presupuesto; negativa = la categoría ha superado lo previsto.

Sheet Presupuesto
B2: PLANIFICADOR DE BODA · PRESUPUESTO
B3: Presupuesto de boda por categoría
B4: Distribuye el coste previsto y conserva la lectura mensual para anticipar los desembolsos.
B6: PRESUPUESTO DE BODA · CELDAS DE COLOR = ENTRADA
B7: Categoría | C7: Enero | D7: Febrero | E7: Marzo | F7: Abril | G7: Mayo | H7: Junio | I7: Julio | J7: Agosto | K7: Septiembre | L7: Octubre | M7: Noviembre | N7: Diciembre | O7: Total
B8: Lugar y ceremonia | C8: 0 | D8: 0 | E8: 2000 | F8: 0 | G8: 1500 | H8: 0 | I8: 0 | J8: 0 | K8: 0 | L8: 0 | M8: 0 | N8: 0 | O8: =SUM(C8:N8) -> 3500
B9: Banquete | C9: 0 | D9: 0 | E9: 0 | F9: 0 | G9: 0 | H9: 5000 | I9: 0 | J9: 0 | K9: 0 | L9: 0 | M9: 0 | N9: 0 | O9: =SUM(C9:N9) -> 5000
B10: Fotografía y vídeo | C10: 0 | D10: 0 | E10: 0 | F10: 0 | G10: 0 | H10: 1800 | I10: 0 | J10: 0 | K10: 0 | L10: 0 | M10: 0 | N10: 0 | O10: =SUM(C10:N10) -> 1800
B11: Música | C11: 0 | D11: 0 | E11: 0 | F11: 0 | G11: 0 | H11: 1200 | I11: 0 | J11: 0 | K11: 0 | L11: 0 | M11: 0 | N11: 0 | O11: =SUM(C11:N11) -> 1200
B12: Decoración y flores | C12: 0 | D12: 0 | E12: 0 | F12: 0 | G12: 0 | H12: 1600 | I12: 0 | J12: 0 | K12: 0 | L12: 0 | M12: 0 | N12: 0 | O12: =SUM(C12:N12) -> 1600
B13: Vestuario y belleza | C13: 300 | D13: 800 | E13: 300 | F13: 0 | G13: 0 | H13: 600 | I13: 0 | J13: 0 | K13: 0 | L13: 0 | M13: 0 | N13: 0 | O13: =SUM(C13:N13) -> 2000
B14: Papelería y detalles | C14: 250 | D14: 250 | E14: 350 | F14: 350 | G14: 400 | H14: 500 | I14: 0 | J14: 0 | K14: 0 | L14: 0 | M14: 0 | N14: 0 | O14: =SUM(C14:N14) -> 2100
B15: TOTAL DE LA BODA | C15: =SUM(C8:C14) -> 550 | D15: =SUM(D8:D14) -> 1050 | E15: =SUM(E8:E14) -> 2650 | F15: =SUM(F8:F14) -> 350 | G15: =SUM(G8:G14) -> 1900 | H15: =SUM(H8:H14) -> 10700 | I15: =SUM(I8:I14) -> 0 | J15: =SUM(J8:J14) -> 0 | ... O15: =SUM(O8:O14) -> 17200
B18: La matriz conserva el patrón mensual/anual de la base: categorías en filas, meses en columnas y total calculado a la derecha. Puedes cambiar los importes sin mover el encuadre.

Sheet Pagos reales
B2: PLANIFICADOR DE BODA · PAGOS REALES
B3: Pagos reales de proveedores
B4: Cada importe se obtiene del registro de proveedores para comparar lo previsto con lo ya pagado.
B6: PAGOS REALES · FÓRMULAS DESDE PROVEEDORES
B7: Categoría | C7: Enero | D7: Febrero | E7: Marzo | F7: Abril | G7: Mayo | H7: Junio | I7: Julio | J7: Agosto | K7: Septiembre | L7: Octubre | M7: Noviembre | N7: Diciembre | O7: Total
B8: =Presupuesto!B8 -> Lugar y ceremonia | C8: =SUMIFS(Proveedores!$G$8:$G$200,Proveedores!$D$8:$D$200,"Pago",Proveedores!$E$8:$E$200,$B8,Proveedores!$C$8:$C$200,C$7) -> 2000 | D8: =SUMIFS(Proveedores!$G$8:$G$200,Proveedores!$D$8:$D$200,"Pago",Proveedores!$E$8:$E$200,$B8,Proveedores!$C$8:$C$200,D$7) -> 0 | E8: =SUMIFS(Proveedores!$G$8:$G$200,Proveedores!$D$8:$D$200,"Pago",Proveedores!$E$8:$E$200,$B8,Proveedores!$C$8:$C$200,E$7) -> 0 | F8: =SUMIFS(Proveedores!$G$8:$G$200,Proveedores!$D$8:$D$200,"Pago",Proveedores!$E$8:$E$200,$B8,Proveedores!$C$8:$C$200,F$7) -> 0 | G8: =SUMIFS(Proveedores!$G$8:$G$200,Proveedores!$D$8:$D$200,"Pago",Proveedores!$E$8:$E$200,$B8,Proveedores!$C$8:$C$200,G$7) -> 0 | H8: =SUMIFS(Proveedores!$G$8:$G$200,Proveedores!$D$8:$D$200,"Pago",Proveedores!$E$8:$E$200,$B8,Proveedores!$C$8:$C$200,H$7) -> 0 | I8: =SUMIFS(Proveedores!$G$8:$G$200,Proveedores!$D$8:$D$200,"Pago",Proveedores!$E$8:$E$200,$B8,Proveedores!$C$8:$C$200,I$7) -> 0 | J8: =SUMIFS(Proveedores!$G$8:$G$200,Proveedores!$D$8:$D$200,"Pago",Proveedores!$E$8:$E$200,$B8,Proveedores!$C$8:$C$200,J$7) -> 0 | ... N8: =SUMIFS(Proveedores!$G$8:$G$200,Proveedores!$D$8:$D$200,"Pago",Proveedores!$E$8:$E$200,$B8,Proveedores!$C$8:$C$200,N$7) -> 0 | O8: =SUM(C8:N8) -> 2000
B9: =Presupuesto!B9 -> Banquete | C9: =SUMIFS(Proveedores!$G$8:$G$200,Proveedores!$D$8:$D$200,"Pago",Proveedores!$E$8:$E$200,$B9,Proveedores!$C$8:$C$200,C$7) -> 0 | D9: =SUMIFS(Proveedores!$G$8:$G$200,Proveedores!$D$8:$D$200,"Pago",Proveedores!$E$8:$E$200,$B9,Proveedores!$C$8:$C$200,D$7) -> 0 | E9: =SUMIFS(Proveedores!$G$8:$G$200,Proveedores!$D$8:$D$200,"Pago",Proveedores!$E$8:$E$200,$B9,Proveedores!$C$8:$C$200,E$7) -> 0 | F9: =SUMIFS(Proveedores!$G$8:$G$200,Proveedores!$D$8:$D$200,"Pago",Proveedores!$E$8:$E$200,$B9,Proveedores!$C$8:$C$200,F$7) -> 0 | G9: =SUMIFS(Proveedores!$G$8:$G$200,Proveedores!$D$8:$D$200,"Pago",Proveedores!$E$8:$E$200,$B9,Proveedores!$C$8:$C$200,G$7) -> 0 | H9: =SUMIFS(Proveedores!$G$8:$G$200,Proveedores!$D$8:$D$200,"Pago",Proveedores!$E$8:$E$200,$B9,Proveedores!$C$8:$C$200,H$7) -> 0 | I9: =SUMIFS(Proveedores!$G$8:$G$200,Proveedores!$D$8:$D$200,"Pago",Proveedores!$E$8:$E$200,$B9,Proveedores!$C$8:$C$200,I$7) -> 0 | J9: =SUMIFS(Proveedores!$G$8:$G$200,Proveedores!$D$8:$D$200,"Pago",Proveedores!$E$8:$E$200,$B9,Proveedores!$C$8:$C$200,J$7) -> 0 | ... N9: =SUMIFS(Proveedores!$G$8:$G$200,Proveedores!$D$8:$D$200,"Pago",Proveedores!$E$8:$E$200,$B9,Proveedores!$C$8:$C$200,N$7) -> 0 | O9: =SUM(C9:N9) -> 0
B10: =Presupuesto!B10 -> Fotografía y vídeo | C10: =SUMIFS(Proveedores!$G$8:$G$200,Proveedores!$D$8:$D$200,"Pago",Proveedores!$E$8:$E$200,$B10,Proveedores!$C$8:$C$200,C$7) -> 0 | D10: =SUMIFS(Proveedores!$G$8:$G$200,Proveedores!$D$8:$D$200,"Pago",Proveedores!$E$8:$E$200,$B10,Proveedores!$C$8:$C$200,D$7) -> 0 | E10: =SUMIFS(Proveedores!$G$8:$G$200,Proveedores!$D$8:$D$200,"Pago",Proveedores!$E$8:$E$200,$B10,Proveedores!$C$8:$C$200,E$7) -> 0 | F10: =SUMIFS(Proveedores!$G$8:$G$200,Proveedores!$D$8:$D$200,"Pago",Proveedores!$E$8:$E$200,$B10,Proveedores!$C$8:$C$200,F$7) -> 600 | G10: =SUMIFS(Proveedores!$G$8:$G$200,Proveedores!$D$8:$D$200,"Pago",Proveedores!$E$8:$E$200,$B10,Proveedores!$C$8:$C$200,G$7) -> 0 | H10: =SUMIFS(Proveedores!$G$8:$G$200,Proveedores!$D$8:$D$200,"Pago",Proveedores!$E$8:$E$200,$B10,Proveedores!$C$8:$C$200,H$7) -> 0 | I10: =SUMIFS(Proveedores!$G$8:$G$200,Proveedores!$D$8:$D$200,"Pago",Proveedores!$E$8:$E$200,$B10,Proveedores!$C$8:$C$200,I$7) -> 0 | J10: =SUMIFS(Proveedores!$G$8:$G$200,Proveedores!$D$8:$D$200,"Pago",Proveedores!$E$8:$E$200,$B10,Proveedores!$C$8:$C$200,J$7) -> 0 | ... N10: =SUMIFS(Proveedores!$G$8:$G$200,Proveedores!$D$8:$D$200,"Pago",Proveedores!$E$8:$E$200,$B10,Proveedores!$C$8:$C$200,N$7) -> 0 | O10: =SUM(C10:N10) -> 600
B11: =Presupuesto!B11 -> Música | C11: =SUMIFS(Proveedores!$G$8:$G$200,Proveedores!$D$8:$D$200,"Pago",Proveedores!$E$8:$E$200,$B11,Proveedores!$C$8:$C$200,C$7) -> 0 | D11: =SUMIFS(Proveedores!$G$8:$G$200,Proveedores!$D$8:$D$200,"Pago",Proveedores!$E$8:$E$200,$B11,Proveedores!$C$8:$C$200,D$7) -> 0 | E11: =SUMIFS(Proveedores!$G$8:$G$200,Proveedores!$D$8:$D$200,"Pago",Proveedores!$E$8:$E$200,$B11,Proveedores!$C$8:$C$200,E$7) -> 0 | F11: =SUMIFS(Proveedores!$G$8:$G$200,Proveedores!$D$8:$D$200,"Pago",Proveedores!$E$8:$E$200,$B11,Proveedores!$C$8:$C$200,F$7) -> 0 | G11: =SUMIFS(Proveedores!$G$8:$G$200,Proveedores!$D$8:$D$200,"Pago",Proveedores!$E$8:$E$200,$B11,Proveedores!$C$8:$C$200,G$7) -> 0 | H11: =SUMIFS(Proveedores!$G$8:$G$200,Proveedores!$D$8:$D$200,"Pago",Proveedores!$E$8:$E$200,$B11,Proveedores!$C$8:$C$200,H$7) -> 0 | I11: =SUMIFS(Proveedores!$G$8:$G$200,Proveedores!$D$8:$D$200,"Pago",Proveedores!$E$8:$E$200,$B11,Proveedores!$C$8:$C$200,I$7) -> 0 | J11: =SUMIFS(Proveedores!$G$8:$G$200,Proveedores!$D$8:$D$200,"Pago",Proveedores!$E$8:$E$200,$B11,Proveedores!$C$8:$C$200,J$7) -> 0 | ... N11: =SUMIFS(Proveedores!$G$8:$G$200,Proveedores!$D$8:$D$200,"Pago",Proveedores!$E$8:$E$200,$B11,Proveedores!$C$8:$C$200,N$7) -> 0 | O11: =SUM(C11:N11) -> 0
B12: =Presupuesto!B12 -> Decoración y flores | C12: =SUMIFS(Proveedores!$G$8:$G$200,Proveedores!$D$8:$D$200,"Pago",Proveedores!$E$8:$E$200,$B12,Proveedores!$C$8:$C$200,C$7) -> 0 | D12: =SUMIFS(Proveedores!$G$8:$G$200,Proveedores!$D$8:$D$200,"Pago",Proveedores!$E$8:$E$200,$B12,Proveedores!$C$8:$C$200,D$7) -> 0 | E12: =SUMIFS(Proveedores!$G$8:$G$200,Proveedores!$D$8:$D$200,"Pago",Proveedores!$E$8:$E$200,$B12,Proveedores!$C$8:$C$200,E$7) -> 0 | F12: =SUMIFS(Proveedores!$G$8:$G$200,Proveedores!$D$8:$D$200,"Pago",Proveedores!$E$8:$E$200,$B12,Proveedores!$C$8:$C$200,F$7) -> 0 | G12: =SUMIFS(Proveedores!$G$8:$G$200,Proveedores!$D$8:$D$200,"Pago",Proveedores!$E$8:$E$200,$B12,Proveedores!$C$8:$C$200,G$7) -> 0 | H12: =SUMIFS(Proveedores!$G$8:$G$200,Proveedores!$D$8:$D$200,"Pago",Proveedores!$E$8:$E$200,$B12,Proveedores!$C$8:$C$200,H$7) -> 0 | I12: =SUMIFS(Proveedores!$G$8:$G$200,Proveedores!$D$8:$D$200,"Pago",Proveedores!$E$8:$E$200,$B12,Proveedores!$C$8:$C$200,I$7) -> 0 | J12: =SUMIFS(Proveedores!$G$8:$G$200,Proveedores!$D$8:$D$200,"Pago",Proveedores!$E$8:$E$200,$B12,Proveedores!$C$8:$C$200,J$7) -> 0 | ... N12: =SUMIFS(Proveedores!$G$8:$G$200,Proveedores!$D$8:$D$200,"Pago",Proveedores!$E$8:$E$200,$B12,Proveedores!$C$8:$C$200,N$7) -> 0 | O12: =SUM(C12:N12) -> 0
B13: =Presupuesto!B13 -> Vestuario y belleza | C13: =SUMIFS(Proveedores!$G$8:$G$200,Proveedores!$D$8:$D$200,"Pago",Proveedores!$E$8:$E$200,$B13,Proveedores!$C$8:$C$200,C$7) -> 0 | D13: =SUMIFS(Proveedores!$G$8:$G$200,Proveedores!$D$8:$D$200,"Pago",Proveedores!$E$8:$E$200,$B13,Proveedores!$C$8:$C$200,D$7) -> 800 | E13: =SUMIFS(Proveedores!$G$8:$G$200,Proveedores!$D$8:$D$200,"Pago",Proveedores!$E$8:$E$200,$B13,Proveedores!$C$8:$C$200,E$7) -> 0 | F13: =SUMIFS(Proveedores!$G$8:$G$200,Proveedores!$D$8:$D$200,"Pago",Proveedores!$E$8:$E$200,$B13,Proveedores!$C$8:$C$200,F$7) -> 0 | G13: =SUMIFS(Proveedores!$G$8:$G$200,Proveedores!$D$8:$D$200,"Pago",Proveedores!$E$8:$E$200,$B13,Proveedores!$C$8:$C$200,G$7) -> 0 | H13: =SUMIFS(Proveedores!$G$8:$G$200,Proveedores!$D$8:$D$200,"Pago",Proveedores!$E$8:$E$200,$B13,Proveedores!$C$8:$C$200,H$7) -> 0 | I13: =SUMIFS(Proveedores!$G$8:$G$200,Proveedores!$D$8:$D$200,"Pago",Proveedores!$E$8:$E$200,$B13,Proveedores!$C$8:$C$200,I$7) -> 0 | J13: =SUMIFS(Proveedores!$G$8:$G$200,Proveedores!$D$8:$D$200,"Pago",Proveedores!$E$8:$E$200,$B13,Proveedores!$C$8:$C$200,J$7) -> 0 | ... N13: =SUMIFS(Proveedores!$G$8:$G$200,Proveedores!$D$8:$D$200,"Pago",Proveedores!$E$8:$E$200,$B13,Proveedores!$C$8:$C$200,N$7) -> 0 | O13: =SUM(C13:N13) -> 800
B14: =Presupuesto!B14 -> Papelería y detalles | C14: =SUMIFS(Proveedores!$G$8:$G$200,Proveedores!$D$8:$D$200,"Pago",Proveedores!$E$8:$E$200,$B14,Proveedores!$C$8:$C$200,C$7) -> 0 | D14: =SUMIFS(Proveedores!$G$8:$G$200,Proveedores!$D$8:$D$200,"Pago",Proveedores!$E$8:$E$200,$B14,Proveedores!$C$8:$C$200,D$7) -> 0 | E14: =SUMIFS(Proveedores!$G$8:$G$200,Proveedores!$D$8:$D$200,"Pago",Proveedores!$E$8:$E$200,$B14,Proveedores!$C$8:$C$200,E$7) -> 350 | F14: =SUMIFS(Proveedores!$G$8:$G$200,Proveedores!$D$8:$D$200,"Pago",Proveedores!$E$8:$E$200,$B14,Proveedores!$C$8:$C$200,F$7) -> 0 | G14: =SUMIFS(Proveedores!$G$8:$G$200,Proveedores!$D$8:$D$200,"Pago",Proveedores!$E$8:$E$200,$B14,Proveedores!$C$8:$C$200,G$7) -> 0 | H14: =SUMIFS(Proveedores!$G$8:$G$200,Proveedores!$D$8:$D$200,"Pago",Proveedores!$E$8:$E$200,$B14,Proveedores!$C$8:$C$200,H$7) -> 0 | I14: =SUMIFS(Proveedores!$G$8:$G$200,Proveedores!$D$8:$D$200,"Pago",Proveedores!$E$8:$E$200,$B14,Proveedores!$C$8:$C$200,I$7) -> 0 | J14: =SUMIFS(Proveedores!$G$8:$G$200,Proveedores!$D$8:$D$200,"Pago",Proveedores!$E$8:$E$200,$B14,Proveedores!$C$8:$C$200,J$7) -> 0 | ... N14: =SUMIFS(Proveedores!$G$8:$G$200,Proveedores!$D$8:$D$200,"Pago",Proveedores!$E$8:$E$200,$B14,Proveedores!$C$8:$C$200,N$7) -> 0 | O14: =SUM(C14:N14) -> 350
B15: TOTAL PAGADO | C15: =SUM(C8:C14) -> 2000 | D15: =SUM(D8:D14) -> 800 | E15: =SUM(E8:E14) -> 350 | F15: =SUM(F8:F14) -> 600 | G15: =SUM(G8:G14) -> 0 | H15: =SUM(H8:H14) -> 0 | I15: =SUM(I8:I14) -> 0 | J15: =SUM(J8:J14) -> 0 | ... O15: =SUM(O8:O14) -> 3750
B18: La hoja sigue el patrón de presupuesto frente a real, pero centraliza los pagos en Proveedores para evitar duplicidades y facilitar la revisión de contratos.

Sheet Proveedores
B2: PLANIFICADOR DE BODA · PROVEEDORES
B3: Registro de proveedores y pagos
B4: Anota cada contrato o desembolso una sola vez; las hojas de análisis se alimentan de este diario.
B6: REGISTRO OPERATIVO · PROVEEDORES Y PAGOS | K6: REGLAS DEL DIARIO
B7: Fecha | C7: Mes | D7: Tipo | E7: Categoría | F7: Concepto | G7: Importe | H7: Pagado por | I7: Estado | K7: Una fila = un contrato, pago o ajuste. Usa Tipo y Estado para que los resúmenes distingan lo comprometido de lo abonado.
B8: 46397 | C8: Enero | D8: Pago | E8: Lugar y ceremonia | F8: Reserva del espacio | G8: 2000 | H8: Pareja | I8: Pagado
B9: 46432 | C9: Febrero | D9: Pago | E9: Vestuario y belleza | F9: Vestido y pruebas | G9: 800 | H9: Pareja | I9: Pagado
B10: 46450 | C10: Marzo | D10: Pago | E10: Papelería y detalles | F10: Invitaciones | G10: 350 | H10: Familia | I10: Pendiente
B11: 46479 | C11: Abril | D11: Pago | E11: Fotografía y vídeo | F11: Reserva fotógrafo | G11: 600 | H11: Pareja | I11: Pendiente
B12: 46527 | C12: Mayo | D12: Ingreso | E12: Banquete | F12: Aportación familiar | G12: 1500 | H12: Familia | I12: Confirmado | K12: Las listas desplegables mantienen consistentes categorías, responsables y estados en todo el libro.
B13: 46557 | C13: Junio | D13: Ajuste | E13: Decoración y flores | F13: Fondo de imprevistos | G13: 300 | H13: Pareja | I13: Pendiente

Sheet Flujo de pagos
B2: PLANIFICADOR DE BODA · FLUJO DE PAGOS
B3: Flujo mensual de pagos
B4: La lectura anual combina presupuesto, ingresos, pagos reales, ajustes y saldo previsto.
B6: LECTURA MENSUAL DE LA BODA
B7: Mes | C7: Presupuesto plan | D7: Ingresos | E7: Pagos previstos | F7: Pagos reales | G7: Ajustes | H7: Saldo previsto | I7: Comentarios | J7: Estado
B8: Enero | C8: =SUM(Presupuesto!C$8:C$14) -> 550 | D8: =SUMIFS(Proveedores!$G$8:$G$200,Proveedores!$D$8:$D$200,"Ingreso",Proveedores!$C$8:$C$200,$B8) -> 0 | E8: =C8 -> 550 | F8: =SUMIFS(Proveedores!$G$8:$G$200,Proveedores!$D$8:$D$200,"Pago",Proveedores!$C$8:$C$200,$B8) -> 2000 | G8: =SUMIFS(Proveedores!$G$8:$G$200,Proveedores!$D$8:$D$200,"Ajuste",Proveedores!$C$8:$C$200,$B8) -> 0 | H8: =C8-F8+D8-G8 -> -1450
B9: Febrero | C9: =SUM(Presupuesto!D$8:D$14) -> 1050 | D9: =SUMIFS(Proveedores!$G$8:$G$200,Proveedores!$D$8:$D$200,"Ingreso",Proveedores!$C$8:$C$200,$B9) -> 0 | E9: =C9 -> 1050 | F9: =SUMIFS(Proveedores!$G$8:$G$200,Proveedores!$D$8:$D$200,"Pago",Proveedores!$C$8:$C$200,$B9) -> 800 | G9: =SUMIFS(Proveedores!$G$8:$G$200,Proveedores!$D$8:$D$200,"Ajuste",Proveedores!$C$8:$C$200,$B9) -> 0 | H9: =C9-F9+D9-G9 -> 250
B10: Marzo | C10: =SUM(Presupuesto!E$8:E$14) -> 2650 | D10: =SUMIFS(Proveedores!$G$8:$G$200,Proveedores!$D$8:$D$200,"Ingreso",Proveedores!$C$8:$C$200,$B10) -> 0 | E10: =C10 -> 2650 | F10: =SUMIFS(Proveedores!$G$8:$G$200,Proveedores!$D$8:$D$200,"Pago",Proveedores!$C$8:$C$200,$B10) -> 350 | G10: =SUMIFS(Proveedores!$G$8:$G$200,Proveedores!$D$8:$D$200,"Ajuste",Proveedores!$C$8:$C$200,$B10) -> 0 | H10: =C10-F10+D10-G10 -> 2300
B11: Abril | C11: =SUM(Presupuesto!F$8:F$14) -> 350 | D11: =SUMIFS(Proveedores!$G$8:$G$200,Proveedores!$D$8:$D$200,"Ingreso",Proveedores!$C$8:$C$200,$B11) -> 0 | E11: =C11 -> 350 | F11: =SUMIFS(Proveedores!$G$8:$G$200,Proveedores!$D$8:$D$200,"Pago",Proveedores!$C$8:$C$200,$B11) -> 600 | G11: =SUMIFS(Proveedores!$G$8:$G$200,Proveedores!$D$8:$D$200,"Ajuste",Proveedores!$C$8:$C$200,$B11) -> 0 | H11: =C11-F11+D11-G11 -> -250
B12: Mayo | C12: =SUM(Presupuesto!G$8:G$14) -> 1900 | D12: =SUMIFS(Proveedores!$G$8:$G$200,Proveedores!$D$8:$D$200,"Ingreso",Proveedores!$C$8:$C$200,$B12) -> 1500 | E12: =C12 -> 1900 | F12: =SUMIFS(Proveedores!$G$8:$G$200,Proveedores!$D$8:$D$200,"Pago",Proveedores!$C$8:$C$200,$B12) -> 0 | G12: =SUMIFS(Proveedores!$G$8:$G$200,Proveedores!$D$8:$D$200,"Ajuste",Proveedores!$C$8:$C$200,$B12) -> 0 | H12: =C12-F12+D12-G12 -> 3400
B13: Junio | C13: =SUM(Presupuesto!H$8:H$14) -> 10700 | D13: =SUMIFS(Proveedores!$G$8:$G$200,Proveedores!$D$8:$D$200,"Ingreso",Proveedores!$C$8:$C$200,$B13) -> 0 | E13: =C13 -> 10700 | F13: =SUMIFS(Proveedores!$G$8:$G$200,Proveedores!$D$8:$D$200,"Pago",Proveedores!$C$8:$C$200,$B13) -> 0 | G13: =SUMIFS(Proveedores!$G$8:$G$200,Proveedores!$D$8:$D$200,"Ajuste",Proveedores!$C$8:$C$200,$B13) -> 300 | H13: =C13-F13+D13-G13 -> 10400
B14: Julio | C14: =SUM(Presupuesto!I$8:I$14) -> 0 | D14: =SUMIFS(Proveedores!$G$8:$G$200,Proveedores!$D$8:$D$200,"Ingreso",Proveedores!$C$8:$C$200,$B14) -> 0 | E14: =C14 -> 0 | F14: =SUMIFS(Proveedores!$G$8:$G$200,Proveedores!$D$8:$D$200,"Pago",Proveedores!$C$8:$C$200,$B14) -> 0 | G14: =SUMIFS(Proveedores!$G$8:$G$200,Proveedores!$D$8:$D$200,"Ajuste",Proveedores!$C$8:$C$200,$B14) -> 0 | H14: =C14-F14+D14-G14 -> 0
B15: Agosto | C15: =SUM(Presupuesto!J$8:J$14) -> 0 | D15: =SUMIFS(Proveedores!$G$8:$G$200,Proveedores!$D$8:$D$200,"Ingreso",Proveedores!$C$8:$C$200,$B15) -> 0 | E15: =C15 -> 0 | F15: =SUMIFS(Proveedores!$G$8:$G$200,Proveedores!$D$8:$D$200,"Pago",Proveedores!$C$8:$C$200,$B15) -> 0 | G15: =SUMIFS(Proveedores!$G$8:$G$200,Proveedores!$D$8:$D$200,"Ajuste",Proveedores!$C$8:$C$200,$B15) -> 0 | H15: =C15-F15+D15-G15 -> 0
B16: Septiembre | C16: =SUM(Presupuesto!K$8:K$14) -> 0 | D16: =SUMIFS(Proveedores!$G$8:$G$200,Proveedores!$D$8:$D$200,"Ingreso",Proveedores!$C$8:$C$200,$B16) -> 0 | E16: =C16 -> 0 | F16: =SUMIFS(Proveedores!$G$8:$G$200,Proveedores!$D$8:$D$200,"Pago",Proveedores!$C$8:$C$200,$B16) -> 0 | G16: =SUMIFS(Proveedores!$G$8:$G$200,Proveedores!$D$8:$D$200,"Ajuste",Proveedores!$C$8:$C$200,$B16) -> 0 | H16: =C16-F16+D16-G16 -> 0
B17: Octubre | C17: =SUM(Presupuesto!L$8:L$14) -> 0 | D17: =SUMIFS(Proveedores!$G$8:$G$200,Proveedores!$D$8:$D$200,"Ingreso",Proveedores!$C$8:$C$200,$B17) -> 0 | E17: =C17 -> 0 | F17: =SUMIFS(Proveedores!$G$8:$G$200,Proveedores!$D$8:$D$200,"Pago",Proveedores!$C$8:$C$200,$B17) -> 0 | G17: =SUMIFS(Proveedores!$G$8:$G$200,Proveedores!$D$8:$D$200,"Ajuste",Proveedores!$C$8:$C$200,$B17) -> 0 | H17: =C17-F17+D17-G17 -> 0
B18: Noviembre | C18: =SUM(Presupuesto!M$8:M$14) -> 0 | D18: =SUMIFS(Proveedores!$G$8:$G$200,Proveedores!$D$8:$D$200,"Ingreso",Proveedores!$C$8:$C$200,$B18) -> 0 | E18: =C18 -> 0 | F18: =SUMIFS(Proveedores!$G$8:$G$200,Proveedores!$D$8:$D$200,"Pago",Proveedores!$C$8:$C$200,$B18) -> 0 | G18: =SUMIFS(Proveedores!$G$8:$G$200,Proveedores!$D$8:$D$200,"Ajuste",Proveedores!$C$8:$C$200,$B18) -> 0 | H18: =C18-F18+D18-G18 -> 0
B19: Diciembre | C19: =SUM(Presupuesto!N$8:N$14) -> 0 | D19: =SUMIFS(Proveedores!$G$8:$G$200,Proveedores!$D$8:$D$200,"Ingreso",Proveedores!$C$8:$C$200,$B19) -> 0 | E19: =C19 -> 0 | F19: =SUMIFS(Proveedores!$G$8:$G$200,Proveedores!$D$8:$D$200,"Pago",Proveedores!$C$8:$C$200,$B19) -> 0 | G19: =SUMIFS(Proveedores!$G$8:$G$200,Proveedores!$D$8:$D$200,"Ajuste",Proveedores!$C$8:$C$200,$B19) -> 0 | H19: =C19-F19+D19-G19 -> 0
B20: TOTAL ANUAL | C20: =SUM(C8:C19) -> 17200 | D20: =SUM(D8:D19) -> 1500 | E20: =SUM(E8:E19) -> 17200 | F20: =SUM(F8:F19) -> 3750 | G20: =SUM(G8:G19) -> 300 | H20: =SUM(H8:H19) -> 14650
B23: El saldo previsto no sustituye una revisión contractual: sirve para ver cuándo se concentran los desembolsos y qué pagos quedan pendientes.

Sheet Checklist
B2: PLANIFICADOR DE BODA · CHECKLIST
B3: Checklist de la boda
B4: Convierte las decisiones importantes en tareas con responsable, fecha y estado.
B6: TAREAS Y MOMENTOS CLAVE
B9: Tarea | C9: Área | D9: Responsable | E9: Fecha límite | F9: Estado | G9: Prioridad | H9: Días | I9: Notas | J9: Progreso
B10: Cerrar contrato del lugar | C10: Lugar | D10: Pareja | E10: 46418 | F10: Confirmado | G10: Alta | H10: =MAX(E10-TODAY(),0) -> 109 | I10: Revisar horarios y montaje | J10: =IF(F10="Confirmado",1,0) -> 1
B11: Enviar invitaciones | C11: Invitados | D11: Familia | E11: 46461 | F11: Pendiente | G11: Alta | H11: =MAX(E11-TODAY(),0) -> 152 | I11: Lista final pendiente | J11: =IF(F11="Confirmado",1,0) -> 0
B12: Confirmar menú y música | C12: Celebración | D12: Pareja | E12: 46527 | F12: Pendiente | G12: Media | H12: =MAX(E12-TODAY(),0) -> 218 | I12: Cita con proveedores | J12: =IF(F12="Confirmado",1,0) -> 0
B16: El checklist comparte la misma retícula de seguimiento de la base, pero cambia metas financieras por decisiones concretas de la boda.

Sheet Invitados
B2: PLANIFICADOR DE BODA · INVITADOS
B3: Invitados y mesas
B4: Controla grupos, confirmaciones, preferencias de menú y distribución de mesas.
B6: LISTA DE INVITADOS
B7: Grupo | C7: Invitados previstos | D7: Confirmados | E7: Menú | F7: Mesa | G7: Estado | H7: Notas
B8: Familia pareja A | C8: 35 | D8: 30 | E8: Estándar | F8: 1 | G8: Confirmado | H8: Pendientes 5 respuestas
B9: Familia pareja B | C9: 30 | D9: 26 | E9: Vegetariano | F9: 2 | G9: Pendiente | H9: Revisar teléfonos
B10: Amigos | C10: 55 | D10: 42 | E10: Mixto | F10: 3 | G10: Pendiente | H10: Confirmar acompañantes
B11: TOTAL | C11: =SUM(C8:C10) -> 120 | D11: =SUM(D8:D10) -> 98
B14: Las cifras de confirmados alimentan la tarjeta del Resumen y ayudan a decidir menú, mesas y cantidad de papelería.

Sheet Listas
B2: PLANIFICADOR DE BODA · LISTAS
B3: Parámetros y catálogos de la boda
B4: Cambia aquí los valores de entrada; las listas alimentan las validaciones del resto del libro.
B6: PARÁMETROS DE LA BODA | E6: MESES | G6: TIPOS | I6: CATEGORÍAS | K6: RESPONSABLES | M6: ESTADOS
B7: Parámetro | C7: Valor | E7: Enero | G7: Pago | I7: Lugar y ceremonia | K7: Pareja | M7: Pendiente
B8: Fecha de boda | C8: 46557 | E8: Febrero | G8: Ingreso | I8: Banquete | K8: Familia | M8: Pagado
B9: Presupuesto objetivo | C9: 18000 | E9: Marzo | G9: Ajuste | I9: Fotografía y vídeo | K9: Proveedor | M9: Confirmado
B10: Invitados previstos | C10: 120 | E10: Abril | I10: Música
B11: Pareja A | C11: Laura | E11: Mayo | I11: Decoración y flores
B12: Pareja B | C12: Álvaro | E12: Junio | I12: Vestuario y belleza
B13: Moneda | C13: EUR | E13: Julio | I13: Papelería y detalles
E14: Agosto
E15: Septiembre
E16: Octubre
E17: Noviembre
E18: Diciembre
E21: Las celdas de entrada definen la boda. Mantén visibles estas listas para adaptar categorías, responsables y estados sin romper las fórmulas.
