Workbook
Name valuevx: 42.314159

Sheet Instrucciones
C4: Instrucciones de Uso
C6: Completar:
C8: 1.- Hoja "Detalle Mensual Planeado":
C9: Aquí se debe detallar por mes lo que se planea tener en cada concepto. No es necesario completar los 12 meses, pueden
C10: completarse la cantidad de meses que quiere compararse
C13: 2.- Hoja "Detalle Mensual Real"
C14: A medida que pasen los meses, se debe completar con el verdadero valor de cada concepto.
C16: Resultado
C17: En la hoja "Presupuesto Consolidado" se resumirá lo planeado versus lo real arrojando la diferencia en cada concepto
C18: Además, mostrará un cuadro del resultado general de ingresos y costos planeados versus reales

Sheet Presupuesto Consolidado
I3: RESUMEN | J3: PLANEADO | K3: REAL | L3: DIFERENCIA
A4: PRESUPUESTO CONSOLIDADO | I4: Total Ingresos | J4: =C9+C14 -> 0 | K4: =D9+D14 -> 0 | L4: =K4-J4 -> 0
I5: Total Costos | J5: =C23+C35+C40+C45 -> 0 | K5: =D23+D35+D40+D45 -> 0 | L5: =K5-J5 -> 0
I6: Ingresos - Costos | J6: =J4-J5 -> 0 | K6: =K4-K5 -> 0 | L6: =K6-J6 -> 0
A7: INGRESOS | C7: PLANEADO | D7: REAL | E7: DIFERENCIA | F7: COMENTARIOS
A9: Ingresos Operativos | C9: =SUM(C10:C12) -> 0 | D9: ='Detalle Mensual Real'!O6 -> 0 | E9: =C9-D9 -> 0
A10: Ventas Producto 1 | C10: ='Detalle Mensual Planeado'!O7 -> 0 | D10: ='Detalle Mensual Real'!O7 -> 0 | E10: =C10-D10 -> 0
A11: Ventas Producto 2 | C11: ='Detalle Mensual Planeado'!O8 -> 0 | D11: ='Detalle Mensual Real'!O8 -> 0 | E11: =C11-D11 -> 0
A12: Servicio 1 | C12: ='Detalle Mensual Planeado'!O9 -> 0 | D12: ='Detalle Mensual Real'!O9 -> 0 | E12: =C12-D12 -> 0
A14: Ingresos No Operativos | C14: =SUM(C15:C19) -> 0 | D14: ='Detalle Mensual Real'!O11 -> 0 | E14: =C14-D14 -> 0
A15: Intereses ganados | C15: ='Detalle Mensual Planeado'!O12 -> 0 | D15: ='Detalle Mensual Real'!O12 -> 0 | E15: =C15-D15 -> 0
A16: Comisiones | C16: ='Detalle Mensual Planeado'!O13 -> 0 | D16: ='Detalle Mensual Real'!O13 -> 0 | E16: =C16-D16 -> 0
A17: Alquiler | C17: ='Detalle Mensual Planeado'!O14 -> 0 | D17: ='Detalle Mensual Real'!O14 -> 0 | E17: =C17-D17 -> 0
A18: Franquicias | C18: ='Detalle Mensual Planeado'!O15 -> 0 | D18: ='Detalle Mensual Real'!O15 -> 0 | E18: =C18-D18 -> 0
A19: Otros | C19: ='Detalle Mensual Planeado'!O16 -> 0 | D19: ='Detalle Mensual Real'!O16 -> 0 | E19: =C19-D19 -> 0
A21: Costos | C21: PLANEADO | D21: REAL | E21: DIFERENCIA | F21: COMENTARIOS
A23: Costos Operativos | C23: =SUM(C24:C33) -> 0 | D23: ='Detalle Mensual Real'!O18 -> 0 | E23: =C23-D23 -> 0
A24: Producción | C24: ='Detalle Mensual Planeado'!O19 -> 0 | D24: ='Detalle Mensual Real'!O19 -> 0 | E24: =C24-D24 -> 0
A25: Depreciación | C25: ='Detalle Mensual Planeado'!O20 -> 0 | D25: ='Detalle Mensual Real'!O20 -> 0 | E25: =C25-D25 -> 0
A26: Envíos | C26: ='Detalle Mensual Planeado'!O21 -> 0 | D26: ='Detalle Mensual Real'!O21 -> 0 | E26: =C26-D26 -> 0
A27: Impuestos | C27: ='Detalle Mensual Planeado'!O22 -> 0 | D27: ='Detalle Mensual Real'!O22 -> 0 | E27: =C27-D27 -> 0
A28: Teléfono | C28: ='Detalle Mensual Planeado'!O23 -> 0 | D28: ='Detalle Mensual Real'!O23 -> 0 | E28: =C28-D28 -> 0
A29: Marketing | C29: ='Detalle Mensual Planeado'!O24 -> 0 | D29: ='Detalle Mensual Real'!O24 -> 0 | E29: =C29-D29 -> 0
A30: Internet | C30: ='Detalle Mensual Planeado'!O25 -> 0 | D30: ='Detalle Mensual Real'!O25 -> 0 | E30: =C30-D30 -> 0
A31: Luz | C31: ='Detalle Mensual Planeado'!O26 -> 0 | D31: ='Detalle Mensual Real'!O26 -> 0 | E31: =C31-D31 -> 0
A32: Gas | C32: ='Detalle Mensual Planeado'!O27 -> 0 | D32: ='Detalle Mensual Real'!O27 -> 0 | E32: =C32-D32 -> 0
A33: Alquiler | C33: ='Detalle Mensual Planeado'!O28 -> 0 | D33: ='Detalle Mensual Real'!O28 -> 0 | E33: =C33-D33 -> 0
A35: Sueldos | C35: =SUM(C36:C38) -> 0 | D35: ='Detalle Mensual Real'!O30 -> 0 | E35: =C35-D35 -> 0
A36: Operarios | C36: ='Detalle Mensual Planeado'!O31 -> 0 | D36: ='Detalle Mensual Real'!O31 -> 0 | E36: =C36-D36 -> 0
A37: Administrativos | C37: ='Detalle Mensual Planeado'!O32 -> 0 | D37: ='Detalle Mensual Real'!O32 -> 0 | E37: =C37-D37 -> 0
A38: Contratados | C38: ='Detalle Mensual Planeado'!O33 -> 0 | D38: ='Detalle Mensual Real'!O33 -> 0 | E38: =C38-D38 -> 0
A40: Gastos de Oficina | C40: =SUM(C41:C43) -> 0 | D40: ='Detalle Mensual Real'!O35 -> 0 | E40: =C40-D40 -> 0
A41: Hojas | C41: ='Detalle Mensual Planeado'!O36 -> 0 | D41: ='Detalle Mensual Real'!O36 -> 0 | E41: =C41-D41 -> 0
A42: Tinta | C42: ='Detalle Mensual Planeado'!O37 -> 0 | D42: ='Detalle Mensual Real'!O37 -> 0 | E42: =C42-D42 -> 0
A43: Fotocopias | C43: ='Detalle Mensual Planeado'!O38 -> 0 | D43: ='Detalle Mensual Real'!O38 -> 0 | E43: =C43-D43 -> 0
A45: Otros Costos | C45: =SUM(C46) -> 0 | D45: ='Detalle Mensual Real'!O40 -> 0 | E45: =C45-D45 -> 0
A46: Otros | C46: ='Detalle Mensual Planeado'!O41 -> 0 | D46: ='Detalle Mensual Real'!O41 -> 0 | E46: =C46-D46 -> 0

Sheet Detalle Mensual Planeado
A3: Planeado | B3: Enero | C3: Febrero | D3: Marzo | E3: Abril | F3: Mayo | G3: Junio | H3: Julio | I3: Agosto | J3: Septiembre | K3: Octubre | L3: Noviembre | M3: Diciembre | O3: Anual
A6: Ingresos Operativos | B6: =SUM(B7:B9) -> 0 | C6: =SUM(C7:C9) -> 0 | D6: =SUM(D7:D9) -> 0 | E6: =SUM(E7:E9) -> 0 | F6: =SUM(F7:F9) -> 0 | G6: =SUM(G7:G9) -> 0 | H6: =SUM(H7:H9) -> 0 | I6: =SUM(I7:I9) -> 0 | ... M6: =SUM(M7:M9) -> 0 | O6: =SUM(B6:M6) -> 0
A7: Ventas Producto 1 | O7: =SUM(B7:M7) -> 0
A8: Ventas Producto 2 | O8: =SUM(B8:M8) -> 0
A9: Servicio 1 | O9: =SUM(B9:M9) -> 0
A11: Ingresos No Operativos | B11: =SUM(B12:B16) -> 0 | C11: =SUM(C12:C16) -> 0 | D11: =SUM(D12:D16) -> 0 | E11: =SUM(E12:E16) -> 0 | F11: =SUM(F12:F16) -> 0 | G11: =SUM(G12:G16) -> 0 | H11: =SUM(H12:H16) -> 0 | I11: =SUM(I12:I16) -> 0 | ... M11: =SUM(M12:M16) -> 0 | O11: =SUM(B11:M11) -> 0
A12: Intereses ganados | O12: =SUM(B12:M12) -> 0
A13: Comisiones | O13: =SUM(B13:M13) -> 0
A14: Alquiler | O14: =SUM(B14:M14) -> 0
A15: Franquicias | O15: =SUM(B15:M15) -> 0
A16: Otros | O16: =SUM(B16:M16) -> 0
A18: Costos Operativos | B18: =SUM(B19:B28) -> 0 | C18: =SUM(C19:C28) -> 0 | D18: =SUM(D19:D28) -> 0 | E18: =SUM(E19:E28) -> 0 | F18: =SUM(F19:F28) -> 0 | G18: =SUM(G19:G28) -> 0 | H18: =SUM(H19:H28) -> 0 | I18: =SUM(I19:I28) -> 0 | ... M18: =SUM(M19:M28) -> 0 | O18: =SUM(B18:M18) -> 0
A19: Producción | O19: =SUM(B19:M19) -> 0
A20: Depreciación | O20: =SUM(B20:M20) -> 0
A21: Envíos | O21: =SUM(B21:M21) -> 0
A22: Impuestos | O22: =SUM(B22:M22) -> 0
A23: Teléfono | O23: =SUM(B23:M23) -> 0
A24: Marketing | O24: =SUM(B24:M24) -> 0
A25: Internet | O25: =SUM(B25:M25) -> 0
A26: Luz | O26: =SUM(B26:M26) -> 0
A27: Gas | O27: =SUM(B27:M27) -> 0
A28: Alquiler | O28: =SUM(B28:M28) -> 0
A30: Sueldos | B30: =SUM(B31:B33) -> 0 | C30: =SUM(C31:C33) -> 0 | D30: =SUM(D31:D33) -> 0 | E30: =SUM(E31:E33) -> 0 | F30: =SUM(F31:F33) -> 0 | G30: =SUM(G31:G33) -> 0 | H30: =SUM(H31:H33) -> 0 | I30: =SUM(I31:I33) -> 0 | ... M30: =SUM(M31:M33) -> 0 | O30: =SUM(B30:M30) -> 0
A31: Operarios | O31: =SUM(B31:M31) -> 0
A32: Administrativos | O32: =SUM(B32:M32) -> 0
A33: Contratados | O33: =SUM(B33:M33) -> 0
A35: Gastos de Oficina | B35: =SUM(B36:B38) -> 0 | C35: =SUM(C36:C38) -> 0 | D35: =SUM(D36:D38) -> 0 | E35: =SUM(E36:E38) -> 0 | F35: =SUM(F36:F38) -> 0 | G35: =SUM(G36:G38) -> 0 | H35: =SUM(H36:H38) -> 0 | I35: =SUM(I36:I38) -> 0 | ... M35: =SUM(M36:M38) -> 0 | O35: =SUM(B35:M35) -> 0
A36: Hojas | O36: =SUM(B36:M36) -> 0
A37: Tinta | O37: =SUM(B37:M37) -> 0
A38: Fotocopias | O38: =SUM(B38:M38) -> 0
A40: Otros Costos | B40: =SUM(B41) -> 0 | C40: =SUM(C41) -> 0 | D40: =SUM(D41) -> 0 | E40: =SUM(E41) -> 0 | F40: =SUM(F41) -> 0 | G40: =SUM(G41) -> 0 | H40: =SUM(H41) -> 0 | I40: =SUM(I41) -> 0 | ... M40: =SUM(M41) -> 0 | O40: =SUM(B40:M40) -> 0
A41: Otros | O41: =SUM(B41:M41) -> 0

Sheet Detalle Mensual Real
A3: Real | B3: Enero | C3: Febrero | D3: Marzo | E3: Abril | F3: Mayo | G3: Junio | H3: Julio | I3: Agosto | J3: Septiembre | K3: Octubre | L3: Noviembre | M3: Diciembre | O3: Anual
A6: Ingresos Operativos | B6: =SUM(B7:B9) -> 0 | C6: =SUM(C7:C9) -> 0 | D6: =SUM(D7:D9) -> 0 | E6: =SUM(E7:E9) -> 0 | F6: =SUM(F7:F9) -> 0 | G6: =SUM(G7:G9) -> 0 | H6: =SUM(H7:H9) -> 0 | I6: =SUM(I7:I9) -> 0 | ... M6: =SUM(M7:M9) -> 0 | O6: =SUM(B6:M6) -> 0
A7: Ventas Producto 1 | O7: =SUM(B7:M7) -> 0
A8: Ventas Producto 2 | O8: =SUM(B8:M8) -> 0
A9: Servicio 1 | O9: =SUM(B9:M9) -> 0
A11: Ingresos No Operativos | B11: =SUM(B12:B16) -> 0 | C11: =SUM(C12:C16) -> 0 | D11: =SUM(D12:D16) -> 0 | E11: =SUM(E12:E16) -> 0 | F11: =SUM(F12:F16) -> 0 | G11: =SUM(G12:G16) -> 0 | H11: =SUM(H12:H16) -> 0 | I11: =SUM(I12:I16) -> 0 | ... M11: =SUM(M12:M16) -> 0 | O11: =SUM(B11:M11) -> 0
A12: Intereses ganados | O12: =SUM(B12:M12) -> 0
A13: Comisiones | O13: =SUM(B13:M13) -> 0
A14: Alquiler | O14: =SUM(B14:M14) -> 0
A15: Franquicias | O15: =SUM(B15:M15) -> 0
A16: Otros | O16: =SUM(B16:M16) -> 0
A18: Costos Operativos | B18: =SUM(B19:B28) -> 0 | C18: =SUM(C19:C28) -> 0 | D18: =SUM(D19:D28) -> 0 | E18: =SUM(E19:E28) -> 0 | F18: =SUM(F19:F28) -> 0 | G18: =SUM(G19:G28) -> 0 | H18: =SUM(H19:H28) -> 0 | I18: =SUM(I19:I28) -> 0 | ... M18: =SUM(M19:M28) -> 0 | O18: =SUM(B18:M18) -> 0
A19: Producción | O19: =SUM(B19:M19) -> 0
A20: Depreciación | O20: =SUM(B20:M20) -> 0
A21: Envíos | O21: =SUM(B21:M21) -> 0
A22: Impuestos | O22: =SUM(B22:M22) -> 0
A23: Teléfono | O23: =SUM(B23:M23) -> 0
A24: Marketing | O24: =SUM(B24:M24) -> 0
A25: Internet | O25: =SUM(B25:M25) -> 0
A26: Luz | O26: =SUM(B26:M26) -> 0
A27: Gas | O27: =SUM(B27:M27) -> 0
A28: Alquiler | O28: =SUM(B28:M28) -> 0
A30: Sueldos | B30: =SUM(B31:B33) -> 0 | C30: =SUM(C31:C33) -> 0 | D30: =SUM(D31:D33) -> 0 | E30: =SUM(E31:E33) -> 0 | F30: =SUM(F31:F33) -> 0 | G30: =SUM(G31:G33) -> 0 | H30: =SUM(H31:H33) -> 0 | I30: =SUM(I31:I33) -> 0 | ... M30: =SUM(M31:M33) -> 0 | O30: =SUM(B30:M30) -> 0
A31: Operarios | O31: =SUM(B31:M31) -> 0
A32: Administrativos | O32: =SUM(B32:M32) -> 0
A33: Contratados | O33: =SUM(B33:M33) -> 0
A35: Gastos de Oficina | B35: =SUM(B36:B38) -> 0 | C35: =SUM(C36:C38) -> 0 | D35: =SUM(D36:D38) -> 0 | E35: =SUM(E36:E38) -> 0 | F35: =SUM(F36:F38) -> 0 | G35: =SUM(G36:G38) -> 0 | H35: =SUM(H36:H38) -> 0 | I35: =SUM(I36:I38) -> 0 | ... M35: =SUM(M36:M38) -> 0 | O35: =SUM(B35:M35) -> 0
A36: Hojas | O36: =SUM(B36:M36) -> 0
A37: Tinta | O37: =SUM(B37:M37) -> 0
A38: Fotocopias | O38: =SUM(B38:M38) -> 0
A40: Otros Costos | B40: =SUM(B41) -> 0 | C40: =SUM(C41) -> 0 | D40: =SUM(D41) -> 0 | E40: =SUM(E41) -> 0 | F40: =SUM(F41) -> 0 | G40: =SUM(G41) -> 0 | H40: =SUM(H41) -> 0 | I40: =SUM(I41) -> 0 | ... M40: =SUM(M41) -> 0 | O40: =SUM(B40:M40) -> 0
A41: Otros | O41: =SUM(B41:M41) -> 0
